MANIFEST.in
README.md
setup.py
MapMatching4GMNS/MapMatching4GMNS.py
MapMatching4GMNS/README.md
MapMatching4GMNS/__init__.py
MapMatching4GMNS/__version__.py
MapMatching4GMNS/map_match_test.py
MapMatching4GMNS.egg-info/PKG-INFO
MapMatching4GMNS.egg-info/SOURCES.txt
MapMatching4GMNS.egg-info/dependency_links.txt
MapMatching4GMNS.egg-info/top_level.txt
MapMatching4GMNS/bin/MapMatching4GMNS.dll
MapMatching4GMNS/bin/MapMatching4GMNS.so
media/0bb1ce8e6ab105f54562c7e711593f64.png
media/0cfa691f959cd8e56021c92b5a50f802.png
media/118bf74177802fd8d8c67f149bf37801.png
media/132c060893d91c6aee76534f323c85cc.png
media/1da34b49eeacb8a53bd98896d6e5953e.png
media/1f78e34e3e8ff4091a1997e44825a503.png
media/1fa21c1d6e8cfdd05b74ce9d3f48bf9f.png
media/22d8257ea35209b83eefefa4eec814c0.png
media/2c3e07d7afef6c519cf7ee331e0bace5.png
media/308de5075f12b12dab40c3309182b047.png
media/337c3df2ec6d98a16fec4df17fd5eebb.png
media/3c75bcdb579896286630db56d8dd9295.png
media/3e5f92dd1b7d253cde1e9f627a6962ce.png
media/4442e2534b75cc10507d353a26516509.png
media/5fdd74e09597da19d58779b8aaa7fc60.png
media/604d110f6a0bdf2a7b1b552b1172e194.png
media/79125164d610fd87d8e4b44e55a73ca8.png
media/7e70321ba5af758f5240d3fcf1478ffd.png
media/8e0b2d1685f355c981069838c424dbf5.png
media/9ece03dedb0310001bdf97a4c4705f8e.png
media/a2000a16b4bdebbe47434db05ce6af53.png
media/a83fb77f142a7b676f7c9f3f80953d0b.png
media/a91eb5417dbf0d19408d851652edef9f.png
media/bb2f8e2690c0478afdef7893260e5a16.png
media/bee94517db0f70b722b56c6fa93f2cfe.png
media/caec124ffd9a88d841b924a0dda3d3b7.png
media/d38aebb8269ae232b9ea5a684558eced.png
media/fbc4d80da3096a50ccd22e8d396b689c.png