Metadata-Version: 2.1
Name: MapMatching4GMNS
Version: 0.2.15
Summary: An open-source, cross-platform, lightweight, and fast Python                 MapMatching4GMNS engine for mapping GPS traces to the underlying network                 using General Modeling Network Specification (GMNS).                 Its most likely path finding algorithm takes about 0.02 seconds to process one GPS trace                 with 50 location points in a large-scale network with 10K nodes.
Home-page: https://github.com/asu-trans-ai-lab/MapMatching4GMNS
Author: Xuesong (Simon) Zhou, Kai (Frank) Zhang, Jiawei Lu
Author-email: xzhou74@asu.edu, xiaomo123zk@gmail.com, jiaweil9@asu.edu
License: UNKNOWN
Platform: windows, linux and MAC
Classifier: Programming Language :: Python :: 3
Classifier: License :: OSI Approved :: Apache Software License
Classifier: Operating System :: OS Independent
